{
  "kind": "singleType",
  "collectionName": "homes",
  "info": {
    "singularName": "home",
    "pluralName": "homes",
    "displayName": "home"
  },
  "options": {
    "draftAndPublish": true
  },
  "pluginOptions": {},
  "attributes": {
    "heading": {
      "type": "string"
    },
    "tagline": {
      "type": "string"
    },
    "featureCategories": {
      "type": "relation",
      "relation": "oneToMany",
      "target": "api::category.category"
    },
    "featurePosts": {
      "type": "relation",
      "relation": "oneToMany",
      "target": "api::post.post"
    }
  }
}
